pretix_tracking_scripts/__init__.py
pretix_tracking_scripts/apps.py
pretix_tracking_scripts/signals.py
pretix_tracking_scripts/templates/pretix_tracking_scripts/google_analytics.html
pretix_tracking_scripts/templates/pretix_tracking_scripts/meta_pixel.html
pretix_tracking_scripts/templates/pretix_tracking_scripts/settings.html
pretix_tracking_scripts/urls.py
pretix_tracking_scripts/views.py
pretix_tracking_scripts-1.0.2.dist-info/METADATA
pretix_tracking_scripts-1.0.2.dist-info/WHEEL
pretix_tracking_scripts-1.0.2.dist-info/entry_points.txt
pretix_tracking_scripts-1.0.2.dist-info/licenses/LICENSE
pretix_tracking_scripts-1.0.2.dist-info/RECORD
