Metadata-Version: 2.4
Name: pretix-tracking-scripts
Version: 1.0.2
Summary: Adds scripts for analytics and conversion tracking to pretix.
License: Apache-2.0
License-File: LICENSE
Author: Kian Cross
Author-email: kian@kiancross.co.uk
Requires-Python: >=3.11,<4.0
Classifier: License :: OSI Approved :: Apache Software License
Classifier: Programming Language :: Python :: 3
Classifier: Programming Language :: Python :: 3.11
Classifier: Programming Language :: Python :: 3.12
Classifier: Programming Language :: Python :: 3.13
Classifier: Programming Language :: Python :: 3.14
Requires-Dist: django (>=4.2.15,<5.0.0)
Requires-Dist: pretix
Project-URL: Repository, https://github.com/kiancross/pretix-tracking-scripts
